orionac_genai/__init__.py
orionac_genai/client.py
orionac_genai-0.1.0.dist-info/METADATA
orionac_genai-0.1.0.dist-info/WHEEL
orionac_genai-0.1.0.dist-info/top_level.txt
orionac_genai-0.1.0.dist-info/RECORD
