Metadata-Version: 2.1
Name: orionac-genai
Version: 0.1.0
Summary: A wrapper for the Orionac-AI API.
Home-page: 
Author: Zakariya
Author-email: contact@orionac-ai.in
Requires-Dist: requests>=2.25.0
